nvx/__init__.py
nvx/main.py
nvx-0.2.0.dist-info/LICENSE
nvx-0.2.0.dist-info/METADATA
nvx-0.2.0.dist-info/WHEEL
nvx-0.2.0.dist-info/entry_points.txt
nvx-0.2.0.dist-info/top_level.txt
nvx-0.2.0.dist-info/RECORD
