Metadata-Version: 2.1
Name: nvx
Version: 0.2.0
Summary: Simple script running nvidia-settings (with anti-tearing) based on your configured layout
Home-page: https://github.com/titarch/nvx
Author: Baptiste Parsy
Author-email: parsybaptiste@gmail.com
Project-URL: repository, https://github.com/titarch/nvx
Classifier: License :: OSI Approved :: MIT License
Classifier: Operating System :: POSIX :: Linux
Classifier: Programming Language :: Python :: 3
Classifier: Topic :: Multimedia :: Video :: Display
Classifier: Topic :: Utilities
Requires-Python: >=3.6
License-File: LICENSE
